mmae/__init__.py
mmae/bregman_divergences.py
mmae/multimodal_autoencoder.py
mmae-0.2.2.dist-info/LICENSE
mmae-0.2.2.dist-info/METADATA
mmae-0.2.2.dist-info/WHEEL
mmae-0.2.2.dist-info/top_level.txt
mmae-0.2.2.dist-info/RECORD
