Metadata-Version: 2.1
Name: mmae
Version: 0.2.2
Summary: Package for multimodal autoencoders with Bregman divergences.
Home-page: https://github.com/asnelt/mmae/
Author: Arno Onken
Author-email: asnelt@asnelt.org
License: GPLv3+
Keywords: autoencoder multimodal deep learning bregman
Platform: UNKNOWN
Classifier: Development Status :: 4 - Beta
Classifier: Intended Audience :: Science/Research
Classifier: License :: OSI Approved :: GNU General Public License v3 or later (GPLv3+)
Classifier: Operating System :: OS Independent
Classifier: Programming Language :: Python
Classifier: Topic :: Scientific/Engineering
Requires-Dist: numpy
Requires-Dist: six
Provides-Extra: keras
Requires-Dist: keras (>=2.3.0) ; extra == 'keras'
Provides-Extra: tensorflow
Requires-Dist: tensorflow (>=2.0.0) ; extra == 'tensorflow'
Provides-Extra: tensorflow-gpu
Requires-Dist: tensorflow-gpu (>=2.0.0) ; extra == 'tensorflow-gpu'
